lit_learn/__init__.py
lit_learn/core/__init__.py
lit_learn/core/objective.py
lit_learn/lit_modules/__init__.py
lit_learn/lit_modules/erm.py
lit_learn/objectives/__init__.py
lit_learn/objectives/multi_objective.py
lit_learn/objectives/adapters/__init__.py
lit_learn/objectives/adapters/losses.py
lit_learn/objectives/classification/__init__.py
lit_learn/objectives/classification/accuracy.py
lit_learn/objectives/classification/cross_entropy.py
lit_learn/objectives/classification/entropy.py
lit_learn/strategies/__init__.py
lit_learn/strategies/scalarization/__init__.py
lit_learn/strategies/scalarization/linear.py
lit_learn/utils/__init__.py
lit_learn-0.1.0.dist-info/licenses/LICENSE
lit_learn-0.1.0.dist-info/METADATA
lit_learn-0.1.0.dist-info/WHEEL
lit_learn-0.1.0.dist-info/top_level.txt
lit_learn-0.1.0.dist-info/RECORD
