Metadata-Version: 2.4
Name: lit-learn
Version: 0.1.0
Summary: A toolkit for multi-task and multi-objective optimization.
Author-email: Anke Tang <tang.anke@foxmail.com>
License: Copyright 2025 Anke Tang
Keywords: optimization,multi-task,multi-objective,machine learning,deep learning
Requires-Python: >=3.10
License-File: LICENSE
Requires-Dist: numpy
Requires-Dist: torch
Requires-Dist: lightning>=2.0
Requires-Dist: torchmetrics
Requires-Dist: hydra-core
Requires-Dist: omegaconf
Provides-Extra: dev
Requires-Dist: pytest>=6.0; extra == "dev"
Requires-Dist: pytest-cov; extra == "dev"
Requires-Dist: black; extra == "dev"
Requires-Dist: flake8; extra == "dev"
Requires-Dist: mypy; extra == "dev"
Requires-Dist: sphinx; extra == "dev"
Requires-Dist: furo; extra == "dev"
Requires-Dist: myst-parser; extra == "dev"
Provides-Extra: docs
Requires-Dist: sphinx>=4.0; extra == "docs"
Requires-Dist: furo; extra == "docs"
Requires-Dist: myst-parser; extra == "docs"
Requires-Dist: numpydoc; extra == "docs"
Dynamic: license-file
